CipherQR/__init__.py
CipherQR/crypto.py
CipherQR/exceptions.py
CipherQR/generator.py
CipherQR/keystore.py
CipherQR/qr_renderer.py
CipherQR/scanner.py
CipherQR/utils.py
tests/__init__.py
tests/test_crypto.py
tests/test_generator_scanner.py
tests/test_keystore.py
cipherqr-1.0.0.dist-info/METADATA
cipherqr-1.0.0.dist-info/WHEEL
cipherqr-1.0.0.dist-info/top_level.txt
cipherqr-1.0.0.dist-info/RECORD
